Metadata-Version: 1.1
Name: tfidfmatcher
Version: 0.0.2
Summary: Fast partial string match using cosine similarity on tf-idf vectors
Home-page: https://github.com/adamhajari/tfidf
Author: Adam Hajari
Author-email: adamhajari@gmail.com
License: MIT
Keywords: partial string matching tfidf
Platform: UNKNOWN
Classifier: Development Status :: 4 - Beta
Classifier: Intended Audience :: Science/Research
Classifier: Topic :: Scientific/Engineering
Classifier: License :: OSI Approved :: MIT License
Classifier: Programming Language :: Python :: 2.7
Classifier: Programming Language :: Python :: 3.4
